ederiv/__init__.py
ederiv/cli.py
ederiv/chem_handlers/__init__.py
ederiv/chem_handlers/mol_handler.py
ederiv/chem_handlers/mol_in_sdf.sdf
ederiv/chem_handlers/smiles_handler.py
ederiv/input_tools/__init__.py
ederiv/input_tools/gvae/__init__.py
ederiv/input_tools/gvae/data_generator.py
ederiv/input_tools/transformers/__init__.py
ederiv/input_tools/transformers/action_gen.py
ederiv/input_tools/transformers/mol_translator.py
ederiv/input_tools/transformers/vocab_builder.py
ederiv/nn_tools/__init__.py
ederiv/nn_tools/auxiliary/batch.py
ederiv/nn_tools/inference/__init__.py
ederiv/nn_tools/inference/model_inference.py
ederiv/nn_tools/loss/__init__.py
ederiv/nn_tools/loss/loss_calculator.py
ederiv/nn_tools/models/__init__.py
ederiv/nn_tools/models/gvae/__init__.py
ederiv/nn_tools/models/transformer/__init__.py
ederiv/nn_tools/models/transformer/mol_transformer.py
ederiv/nn_tools/models/transformer/utils.py
ederiv/nn_tools/trainers/__init__.py
ederiv/nn_tools/trainers/nn_trainer.py
ederiv/optm_tools/__init__.py
ederiv/optm_tools/optm_interface.py
ederiv/optm_tools/obj_funs/__init__.py
ederiv/optm_tools/strategies/meta-heuristic/ga/__init__.py
ederiv/optm_tools/strategies/meta-heuristic/ga/ga.py
ederiv/output_tools/__init__.py
ederiv/output_tools/save_run.py
ederiv/sys_tools/__init__.py
ederiv/sys_tools/model_analyze.py
ederiv2-0.1.4.dist-info/METADATA
ederiv2-0.1.4.dist-info/WHEEL
ederiv2-0.1.4.dist-info/entry_points.txt
ederiv2-0.1.4.dist-info/top_level.txt
ederiv2-0.1.4.dist-info/RECORD
