Metadata-Version: 2.4
Name: ederiv2
Version: 0.1.4
Summary: A molecular graph generation and analysis toolkit using Graph Neural Networks
Home-page: https://github.com/yourusername/eDeriv2
Author: eDeriv2 Team
Author-email: eDeriv2 Team <your.email@example.com>
Maintainer-email: eDeriv2 Team <your.email@example.com>
License: MIT
Project-URL: Homepage, https://github.com/yourusername/eDeriv2
Project-URL: Documentation, https://github.com/yourusername/eDeriv2#readme
Project-URL: Repository, https://github.com/yourusername/eDeriv2
Project-URL: Bug Tracker, https://github.com/yourusername/eDeriv2/issues
Keywords: molecular-graphs,graph-neural-networks,chemistry,machine-learning,drug-discovery
Classifier: Development Status :: 3 - Alpha
Classifier: Intended Audience :: Science/Research
Classifier: Topic :: Scientific/Engineering :: Artificial Intelligence
Classifier: Topic :: Scientific/Engineering :: Chemistry
Classifier: License :: OSI Approved :: MIT License
Classifier: Programming Language :: Python :: 3
Classifier: Programming Language :: Python :: 3.10
Classifier: Programming Language :: Python :: 3.11
Classifier: Programming Language :: Python :: 3.12
Classifier: Operating System :: OS Independent
Requires-Python: >=3.9
Requires-Dist: torch>=1.9.0
Requires-Dist: dgl>=0.1.0
Requires-Dist: numpy>=1.21.0
Requires-Dist: pandas>=1.3.0
Requires-Dist: matplotlib>=3.5.0
Requires-Dist: scikit-learn>=1.0.0
Requires-Dist: scipy>=1.7.0
Requires-Dist: networkx>=2.6.0
Requires-Dist: tqdm>=4.62.0
Requires-Dist: tensorboard>=2.7.0
Requires-Dist: torchmetrics>=0.7.0
Provides-Extra: dev
Requires-Dist: pytest>=6.0; extra == "dev"
Requires-Dist: pytest-cov>=2.0; extra == "dev"
Requires-Dist: black>=21.0; extra == "dev"
Requires-Dist: flake8>=3.8; extra == "dev"
Requires-Dist: mypy>=0.800; extra == "dev"
Provides-Extra: docs
Requires-Dist: sphinx>=4.0; extra == "docs"
Requires-Dist: sphinx-rtd-theme>=1.0; extra == "docs"
Requires-Dist: myst-parser>=0.15; extra == "docs"
Provides-Extra: rdkit
Requires-Dist: rdkit-pypi>=2022.9.1; extra == "rdkit"
Provides-Extra: full
Requires-Dist: seaborn>=0.11.0; extra == "full"
Requires-Dist: plotly>=5.0.0; extra == "full"
Requires-Dist: ipython>=7.0.0; extra == "full"
Requires-Dist: jupyter>=1.0.0; extra == "full"
Requires-Dist: notebook>=6.4.0; extra == "full"
Requires-Dist: rdkit-pypi>=2022.9.1; extra == "full"
Dynamic: author
Dynamic: home-page
Dynamic: requires-python
